{"pkg_name": "com.gau.go.launcherex.theme.Next2", "api_calls": "{\"args\":[\"ReceiverData{intent=Intent { act=com.gau.go.launcherex.action.inactive_apply_theme_flag flg=0x10 cmp=com.gau.go.launcherex.theme.Next2/.ThemeControlReceiver (has extras) } packageName=com.gau.go.launcherex.theme.Next2 resultCode=-1 resultData=null resultExtras=null}\"],\"method\":\"handleReceiver\",\"type\":\"binder\",\"class\":\"android.app.ActivityThread\",\"timestamp\":1514929395648},{\"args\":[{\"cmp\":\"com.gau.go.launcherex.theme.Next2/com.gau.go.launcherex.theme.Next2.ViewPageActivity\"}],\"method\":\"startActivity\",\"type\":\"binder\",\"class\":\"android.app.Activity\",\"timestamp\":1514929378079},{\"args\":[{\"cmp\":\"com.gau.go.launcherex.theme.Next2/com.gau.go.launcherex.theme.Next2.ViewPageActivity\"}],\"method\":\"startActivity\",\"type\":\"binder\",\"class\":\"android.app.Activity\",\"timestamp\":1514929365098},{\"args\":[\"gsm.sim.operator.iso-country\"],\"result\":\"\",\"method\":\"get\",\"type\":\"content\",\"class\":\"android.os.SystemProperties\",\"timestamp\":1514929395630},{\"args\":[\"is_first_open\",\"false\"],\"result\":{\"mClear\":false,\"mModified\":{\"is_first_open\":false}},\"method\":\"putBoolean\",\"type\":\"globals\",\"class\":\"android.app.SharedPreferencesImpl$EditorImpl\",\"timestamp\":1514929365079},{\"args\":[\"gsm.sim.operator.iso-country\"],\"result\":\"\",\"method\":\"get\",\"type\":\"content\",\"class\":\"android.os.SystemProperties\",\"timestamp\":1514929365072},{\"args\":[\"ro.config.low_ram\",\"false\"],\"result\":\"false\",\"method\":\"get\",\"type\":\"content\",\"class\":\"android.os.SystemProperties\",\"timestamp\":1514929365181},{\"args\":[\"ro.config.low_ram\",\"false\"],\"result\":\"false\",\"method\":\"get\",\"type\":\"content\",\"class\":\"android.os.SystemProperties\",\"timestamp\":1514929365176},{\"args\":[\"debug.second-display.pkg\"],\"result\":\"\",\"method\":\"get\",\"type\":\"content\",\"class\":\"android.os.SystemProperties\",\"timestamp\":1514929365059},{\"args\":[\"ReceiverData{intent=Intent { act=com.gau.go.launcherex.action.inactive_apply_theme_flag flg=0x10 cmp=com.gau.go.launcherex.theme.Next2/.ThemeControlReceiver (has extras) } packageName=com.gau.go.launcherex.theme.Next2 resultCode=-1 resultData=null resultExtras=null}\"],\"method\":\"handleReceiver\",\"type\":\"binder\",\"class\":\"android.app.ActivityThread\",\"timestamp\":1514929378082},{\"args\":[],\"result\":\"\",\"method\":\"getSimCountryIso\",\"type\":\"fingerprint\",\"class\":\"android.telephony.TelephonyManager\",\"timestamp\":1514929395631},{\"args\":[\"ReceiverData{intent=Intent { act=com.gau.go.launcherex.action.inactive_apply_theme_flag flg=0x10 cmp=com.gau.go.launcherex.theme.Next2/.ThemeControlReceiver (has extras) } packageName=com.gau.go.launcherex.theme.Next2 resultCode=-1 resultData=null resultExtras=null}\"],\"method\":\"handleReceiver\",\"type\":\"binder\",\"class\":\"android.app.ActivityThread\",\"timestamp\":1514929365112},{\"args\":[\"ro.config.low_ram\",\"false\"],\"result\":\"false\",\"method\":\"get\",\"type\":\"content\",\"class\":\"android.os.SystemProperties\",\"timestamp\":1514929365177},{\"args\":[\"debug.second-display.pkg\"],\"result\":\"\",\"method\":\"get\",\"type\":\"content\",\"class\":\"android.os.SystemProperties\",\"timestamp\":1514929395613},{\"args\":[\"debug.second-display.pkg\"],\"result\":\"\",\"method\":\"get\",\"type\":\"content\",\"class\":\"android.os.SystemProperties\",\"timestamp\":1514929404362},{\"args\":[\"debug.second-display.pkg\"],\"result\":\"\",\"method\":\"get\",\"type\":\"content\",\"class\":\"android.os.SystemProperties\",\"timestamp\":1514929365170},{\"args\":[\"debug.second-display.pkg\"],\"result\":\"\",\"method\":\"get\",\"type\":\"content\",\"class\":\"android.os.SystemProperties\",\"timestamp\":1514929378057},{\"args\":[\"/data/user/0/com.gau.go.launcherex.theme.Next2/shared_prefs/theme.xml\",\"577\"],\"result\":{\"descriptor\":16},\"method\":\"open\",\"type\":\"file\",\"class\":\"libcore.io.IoBridge\",\"timestamp\":1514929365103},{\"args\":[\"gsm.sim.operator.iso-country\"],\"result\":\"\",\"method\":\"get\",\"type\":\"content\",\"class\":\"android.os.SystemProperties\",\"timestamp\":1514929378072},{\"args\":[\"apply_current_theme\",\"false\"],\"result\":{\"mClear\":false,\"mModified\":{\"apply_current_theme\":false}},\"method\":\"putBoolean\",\"type\":\"globals\",\"class\":\"android.app.SharedPreferencesImpl$EditorImpl\",\"timestamp\":1514929378080},{\"args\":[\"ro.config.low_ram\",\"false\"],\"result\":\"false\",\"method\":\"get\",\"type\":\"content\",\"class\":\"android.os.SystemProperties\",\"timestamp\":1514929365263},{\"args\":[{\"cmp\":\"com.gau.go.launcherex.theme.Next2/com.gau.go.launcherex.theme.Next2.ViewPageActivity\"}],\"method\":\"startActivity\",\"type\":\"binder\",\"class\":\"android.app.Activity\",\"timestamp\":1514929365097},{\"args\":[],\"result\":\"\",\"method\":\"getSimCountryIso\",\"type\":\"fingerprint\",\"class\":\"android.telephony.TelephonyManager\",\"timestamp\":1514929365073},{\"args\":[\"apply_current_theme\",\"false\"],\"result\":{\"mClear\":false,\"mModified\":{\"apply_current_theme\":false}},\"method\":\"putBoolean\",\"type\":\"globals\",\"class\":\"android.app.SharedPreferencesImpl$EditorImpl\",\"timestamp\":1514929365100},{\"args\":[\"ro.config.low_ram\",\"false\"],\"result\":\"false\",\"method\":\"get\",\"type\":\"content\",\"class\":\"android.os.SystemProperties\",\"timestamp\":1514929365175},{\"args\":[\"/data/user/0/com.gau.go.launcherex.theme.Next2/shared_prefs/open_theme.xml\",\"577\"],\"result\":{\"descriptor\":15},\"method\":\"open\",\"type\":\"file\",\"class\":\"libcore.io.IoBridge\",\"timestamp\":1514929365082},{\"args\":[{\"cmp\":\"com.gau.go.launcherex.theme.Next2/com.gau.go.launcherex.theme.Next2.ViewPageActivity\"}],\"method\":\"startActivity\",\"type\":\"binder\",\"class\":\"android.app.Activity\",\"timestamp\":1514929395637},{\"args\":[\"apply_current_theme\",\"false\"],\"result\":{\"mClear\":false,\"mModified\":{\"apply_current_theme\":false}},\"method\":\"putBoolean\",\"type\":\"globals\",\"class\":\"android.app.SharedPreferencesImpl$EditorImpl\",\"timestamp\":1514929395639},{\"args\":[],\"result\":\"\",\"method\":\"getSimCountryIso\",\"type\":\"fingerprint\",\"class\":\"android.telephony.TelephonyManager\",\"timestamp\":1514929378073}"}